rft/__init__.py
rft/i3wm.py
rft/rft.py
rft/version.py
rft/window_manager.py
rft/bin/main.py
rofi_tmux-0.4.dist-info/LICENSE
rofi_tmux-0.4.dist-info/METADATA
rofi_tmux-0.4.dist-info/WHEEL
rofi_tmux-0.4.dist-info/entry_points.txt
rofi_tmux-0.4.dist-info/top_level.txt
rofi_tmux-0.4.dist-info/RECORD
