Metadata-Version: 2.1
Name: rofi-tmux
Version: 0.4
Summary: Quickly manages tmux sessions, windows and tmuxinator projects on Rofi
Home-page: http://github.com/viniarck/rofi-tmux
Author: Vinicius Arcanjo
Author-email: viniarck@gmail.com
License: MIT
Keywords: rofi tmux tmuxinator i3 manage switch
License-File: LICENSE
Requires-Dist: python-rofi ==1.0.1
Requires-Dist: libtmux >=0.37.0
Requires-Dist: i3ipc >=2.0.1
Requires-Dist: click
